{
  "main": "Главная",
  "about": "О компании",
  "serves": "Услуги",
  "gallery": "Галерея",
  "contact": "Контакты",
  "servies":"Наши услуги",
   "call":"Звоните в любое время",
  "send":"Написать на email",
  "aboutUs":"О нас",
  "footMenu":"Быстрое меню",
  "work":"Наши работы",
  "address":"г. Ташкент, ул. Элбек, 61",
  "footerText":"Инновационные решения в рекламе и полиграфии с 2010 года — теперь и в Центральной Азии.",
  "desAbout":"С 2010 года наша компания предлагает инновационные решения в сфере рекламы и полиграфии в Турции. Мы постоянно совершенствуемся, чтобы предоставлять услуги, максимально соответствующие потребностям наших клиентов. В 2022 году мы сделали шаг вперёд в международном развитии, построив современный завод в Ташкенте (Узбекистан) площадью 2000 м². С нашей новой производственной базой мы стремимся вывести наш подход к высококачественному производству и оперативному обслуживанию на рынок Центральной Азии, предоставляя профессиональные рекламные решения для клиентов в регионе. Благодаря мощной инфраструктуре и опытной команде, мы всегда ставим удовлетворенность клиентов на первое место и играем ведущую роль в отрасли. Если у вас есть дополнительные вопросы или нужна информация — свяжитесь с нами!"
}